CHANGES.rst
MANIFEST.in
README.rst
setup.py
collective/__init__.py
collective.simpleintranetworkflow.egg-info/PKG-INFO
collective.simpleintranetworkflow.egg-info/SOURCES.txt
collective.simpleintranetworkflow.egg-info/dependency_links.txt
collective.simpleintranetworkflow.egg-info/entry_points.txt
collective.simpleintranetworkflow.egg-info/namespace_packages.txt
collective.simpleintranetworkflow.egg-info/not-zip-safe
collective.simpleintranetworkflow.egg-info/requires.txt
collective.simpleintranetworkflow.egg-info/top_level.txt
collective/simpleintranetworkflow/__init__.py
collective/simpleintranetworkflow/configure.zcml
collective/simpleintranetworkflow/locales/plone.pot
collective/simpleintranetworkflow/locales/de/LC_MESSAGES/plone.po
collective/simpleintranetworkflow/profiles/default/metadata.xml
collective/simpleintranetworkflow/profiles/default/workflows.xml
collective/simpleintranetworkflow/profiles/default/workflows/simple_intranet_workflow/definition.xml
collective/simpleintranetworkflow/profiles/uninstall/workflows.xml
docs/LICENSE-GPL.rst