Metadata-Version: 1.1
Name: collective.simpleintranetworkflow
Version: 1.0.1
Summary: Simple Intranet/Extranet workflow.
Home-page: https://github.com/collective/collective.simpleintranetworkflow
Author: Johannes Raggam
Author-email: raggam-nl@adm.at
License: GPL
Keywords: plone workflow
Platform: UNKNOWN
Classifier: Framework :: Plone
Classifier: Programming Language :: Python
